ashborn/__init__.py
ashborn/main.py
ashborn/data/ML TS XAI HC/HC/Ex7.ipynb
ashborn/data/ML TS XAI HC/HC/Ex8.ipynb
ashborn/data/ML TS XAI HC/HC/Exp_11 .ipynb
ashborn/data/ML TS XAI HC/HC/ex1.ipynb
ashborn/data/ML TS XAI HC/HC/ex10.ipynb
ashborn/data/ML TS XAI HC/HC/ex2.ipynb
ashborn/data/ML TS XAI HC/HC/ex3.ipynb
ashborn/data/ML TS XAI HC/HC/ex4.ipynb
ashborn/data/ML TS XAI HC/HC/ex5.ipynb
ashborn/data/ML TS XAI HC/HC/ex6.ipynb
ashborn/data/ML TS XAI HC/HC/ex9.ipynb
ashborn/data/ML TS XAI HC/HC/data/diabetes.csv
ashborn/data/ML TS XAI HC/HC/data/lung.jpeg
ashborn/data/ML TS XAI HC/ML/1. PCA - EDA.ipynb
ashborn/data/ML TS XAI HC/ML/2. KNN Classifier.ipynb
ashborn/data/ML TS XAI HC/ML/3. Linear Discriminant Analysis.ipynb
ashborn/data/ML TS XAI HC/ML/4. Linear Regression.ipynb
ashborn/data/ML TS XAI HC/ML/5. Logistic Regression.ipynb
ashborn/data/ML TS XAI HC/ML/6. Bayesian Classifier.ipynb
ashborn/data/ML TS XAI HC/ML/SYSTEM32/Ex10_CNN.ipynb
ashborn/data/ML TS XAI HC/ML/SYSTEM32/Ex11.ipynb
ashborn/data/ML TS XAI HC/ML/SYSTEM32/Ex11_HMM.ipynb
ashborn/data/ML TS XAI HC/ML/SYSTEM32/Ex1_PCA_and_EDA.ipynb
ashborn/data/ML TS XAI HC/ML/SYSTEM32/Ex2_KNN.ipynb
ashborn/data/ML TS XAI HC/ML/SYSTEM32/Ex3_LDA.ipynb
ashborn/data/ML TS XAI HC/ML/SYSTEM32/Ex4_LinearRegression.ipynb
ashborn/data/ML TS XAI HC/ML/SYSTEM32/Ex5_Logistic_Regression.ipynb
ashborn/data/ML TS XAI HC/ML/SYSTEM32/Ex6_BassianClassifier.ipynb
ashborn/data/ML TS XAI HC/ML/SYSTEM32/Ex7_SVM.ipynb
ashborn/data/ML TS XAI HC/ML/SYSTEM32/Ex8_MLP.ipynb
ashborn/data/ML TS XAI HC/ML/SYSTEM32/Ex9_Ridge_and_Lasso.ipynb
ashborn/data/ML TS XAI HC/ML/SYSTEM32/HMM.ipynb
ashborn/data/ML TS XAI HC/ML/SYSTEM32/HMM2.ipynb
ashborn/data/ML TS XAI HC/ML/SYSTEM32/Ridge_Lasso.ipynb
ashborn/data/ML TS XAI HC/ML/SYSTEM32/Updated_Untitled.ipynb
ashborn/data/ML TS XAI HC/ML/SYSTEM32/heart.csv
ashborn/data/ML TS XAI HC/ML/SYSTEM32/hmm_2.o.ipynb
ashborn/data/ML TS XAI HC/ML/SYSTEM32/img_load.ipynb
dalx-0.4.dist-info/licenses/LICENSE.txt
dalx-0.4.dist-info/METADATA
dalx-0.4.dist-info/WHEEL
dalx-0.4.dist-info/top_level.txt
dalx-0.4.dist-info/RECORD
